signature_dispatch.py
signature_dispatch-1.0.0.dist-info/LICENSE.txt
signature_dispatch-1.0.0.dist-info/WHEEL
signature_dispatch-1.0.0.dist-info/METADATA
signature_dispatch-1.0.0.dist-info/RECORD
