Metadata-Version: 2.1
Name: signature_dispatch
Version: 1.0.0
Summary: Execute the first function that matches the given arguments.
Home-page: https://github.com/kalekundert/signature_dispatch
Author: Kale Kundert
Author-email: kale@thekunderts.net
Requires-Python: ~=3.6
Classifier: Programming Language :: Python :: 3
Classifier: License :: OSI Approved :: MIT License
Requires-Dist: typeguard
Requires-Dist: sphinx ; extra == "doc"
Requires-Dist: sphinx_rtd_theme ; extra == "doc"
Requires-Dist: autoclasstoc ; extra == "doc"
Requires-Dist: pytest ; extra == "test"
Requires-Dist: pytest-cov ; extra == "test"
Requires-Dist: coveralls ; extra == "test"
Project-URL: Bug Tracker, https://github.com/kalekundert/signature_dispatch/issues
Project-URL: Continuous Integration, https://github.com/kalekundert/signature_dispatch/actions
Project-URL: Documentation, https://signature_dispatch.readthedocs.io/en/latest/
Project-URL: Test Coverage, https://coveralls.io/github/kalekundert/signature_dispatch
Project-URL: Version Control, https://github.com/kalekundert/signature_dispatch
Provides-Extra: doc
Provides-Extra: test
